teddi/__init__.py
teddi-0.0.1.dist-info/LICENSE
teddi-0.0.1.dist-info/METADATA
teddi-0.0.1.dist-info/WHEEL
teddi-0.0.1.dist-info/top_level.txt
teddi-0.0.1.dist-info/RECORD
