Metadata-Version: 2.1
Name: teddi
Version: 0.0.1
Summary: An automated testing tool intended for discord bots.
Home-page: https://github.com/baileymnm1999/teddi
Author: Bailey Morgan
Author-email: bailey.mccarty.morgan@gmail.com
License: UNKNOWN
Platform: UNKNOWN
Classifier: Programming Language :: Python :: 3
Classifier: License :: OSI Approved :: MIT License
Classifier: Operating System :: OS Independent
